sag_py_web_common/__init__.py
sag_py_web_common/default_route.py
sag_py_web_common/filtered_access_logger.py
sag_py_web_common/json_exception_handler.py
sag_py_web_common/py.typed
sag_py_web_common/response_content.py
sag_py_web_common-1.0.6.dist-info/licenses/LICENSE.txt
sag_py_web_common-1.0.6.dist-info/METADATA
sag_py_web_common-1.0.6.dist-info/WHEEL
sag_py_web_common-1.0.6.dist-info/top_level.txt
sag_py_web_common-1.0.6.dist-info/RECORD
