Metadata-Version: 2.4
Name: sag-py-web-common
Version: 1.0.6
Summary: Small helper functions for web projects
Home-page: https://github.com/SamhammerAG/sag_py_web_common
Author: Samhammer AG
Author-email: support@samhammer.de
License: MIT
Project-URL: Documentation, https://github.com/SamhammerAG/sag_py_web_common
Project-URL: Bug Reports, https://github.com/SamhammerAG/sag_py_web_common/issues
Project-URL: Source, https://github.com/SamhammerAG/sag_py_web_common
Keywords: fastapi,web,helper,common
Classifier: Programming Language :: Python :: 3
Classifier: License :: OSI Approved :: MIT License
Classifier: Operating System :: OS Independent
Classifier: Topic :: Software Development :: Libraries :: Python Modules
Classifier: Topic :: Software Development :: Libraries
Classifier: Topic :: Software Development
Requires-Python: >=3.12
License-File: LICENSE.txt
Requires-Dist: asgi-logger>=0.1.0
Requires-Dist: fastapi<1,>=0.115.12
Requires-Dist: starlette>=0.46.2
Provides-Extra: dev
Requires-Dist: anyio>=4.9.0; extra == "dev"
Requires-Dist: build>=1.2.2.post1; extra == "dev"
Requires-Dist: coverage; extra == "dev"
Requires-Dist: coverage-lcov; extra == "dev"
Requires-Dist: flake8>=7.2.0; extra == "dev"
Requires-Dist: httpx>=0.28.1; extra == "dev"
Requires-Dist: mock; extra == "dev"
Requires-Dist: mypy; extra == "dev"
Requires-Dist: pytest; extra == "dev"
Requires-Dist: pytest-asyncio; extra == "dev"
Requires-Dist: pytest-cov; extra == "dev"
Requires-Dist: starlette>=0.46.2; extra == "dev"
Requires-Dist: toml; extra == "dev"
Requires-Dist: types-mock; extra == "dev"
Requires-Dist: zipp>=3.21.0; extra == "dev"
Dynamic: author
Dynamic: author-email
Dynamic: classifier
Dynamic: description
Dynamic: description-content-type
Dynamic: home-page
Dynamic: keywords
Dynamic: license
Dynamic: license-file
Dynamic: project-url
Dynamic: provides-extra
Dynamic: requires-dist
Dynamic: requires-python
Dynamic: summary
